lib.py
main.py
metrics.py
ecoworthy_logger-1.0.0.dist-info/licenses/LICENSE
ecoworthy_logger-1.0.0.dist-info/METADATA
ecoworthy_logger-1.0.0.dist-info/WHEEL
ecoworthy_logger-1.0.0.dist-info/top_level.txt
ecoworthy_logger-1.0.0.dist-info/RECORD
