Metadata-Version: 2.4
Name: ecoworthy-logger
Version: 1.0.0
Summary: Utility to scrape battery data off of Ecoworthy batteries, or any compatible JBD BMS
Author-email: Shahbaz Momi <ssmomi@uwaterloo.ca>
License-Expression: GPL-3.0-or-later
Requires-Python: >=3.13
License-File: LICENSE
Requires-Dist: attrs>=25.4.0
Requires-Dist: bluepy>=1.3.0
Requires-Dist: construct>=2.10.70
Requires-Dist: prometheus-client>=0.24.1
Requires-Dist: typer>=0.21.1
Dynamic: license-file
